pdbacktester/__init__.py
pdbacktester/backtest_result.py
pdbacktester/backtester.py
pdbacktester/constants.py
pdbacktester/errors.py
pdbacktester/evaluation.py
pdbacktester/function_registry.py
pdbacktester/functions.py
pdbacktester/mappings.py
pdbacktester/series_container.py
pdbacktester-0.0.2.dist-info/METADATA
pdbacktester-0.0.2.dist-info/WHEEL
pdbacktester-0.0.2.dist-info/top_level.txt
pdbacktester-0.0.2.dist-info/RECORD
