Metadata-Version: 2.1
Name: pdbacktester
Version: 0.0.2
Summary: Simple backtesting engine for pandas.
License: UNKNOWN
Platform: UNKNOWN
Requires-Dist: pandas
Requires-Dist: pandera
